Ex9/codes/TCAM.v
`define data_size 16
`define address_line 4

module TCAM (input_data, clk, match_address, match_found);

parameter data_size = `data_size;
parameter address_line = `address_line;

input clk;
input [data_size-1:0] input_data;
output reg [address_line-1:0] match_address;
output reg match_found;

reg [data_size-1:0] register_file [(1 << address_line)-1:0];
reg [data_size-1:0] dont_care_register_file [(1 << address_line)-1:0];
reg [data_size-1:0] data;
reg [data_size-1:0] mask;

initial begin
    register_file[0] = 16'b1010101010101010;
    register_file[1] = 16'b1001001001001001;
    register_file[2] = 16'b1100110011001100;
    register_file[3] = 16'b1110001110001110;
    register_file[4] = 16'b1001110010100011;
    register_file[5] = 16'b0101010101010101;
    register_file[6] = 16'b1111111111111111;
    register_file[7] = 16'b0000000000000000;
    register_file[8] = 16'b1010010110100101;
    register_file[9] = 16'b1001100110011001;
    register_file[10] = 16'b0011110000111100;
    register_file[11] = 16'b1010101001010101;
    register_file[12] = 16'b0011011110110110;
    register_file[13] = 16'b1100111000111100;
    register_file[14] = 16'b1001011001011001;
    register_file[15] = 16'b0011010011010011;

    dont_care_register_file[0] = 16'b1111111111111111;
    dont_care_register_file[1] = 16'b1111111111111111;
    dont_care_register_file[2] = 16'b1100111111001111;
    dont_care_register_file[3] = 16'b1100111111001111;
    dont_care_register_file[4] = 16'b0011110000111100;
    dont_care_register_file[5] = 16'b0011110000111100;
    dont_care_register_file[6] = 16'b1000111110001111;
    dont_care_register_file[7] = 16'b1000111110001111;
    dont_care_register_file[8] = 16'b1111111111111111;
    dont_care_register_file[9] = 16'b1111111111111111;
    dont_care_register_file[10] = 16'b1100111111001111;
    dont_care_register_file[11] = 16'b1100111111001111;
    dont_care_register_file[12] = 16'b0011110000111100;
    dont_care_register_file[13] = 16'b0011110000111100;
    dont_care_register_file[14] = 16'b1000111110001111;
    dont_care_register_file[15] = 16'b1000111110001111;
end

integer i, j, match_count;

always @(posedge clk) begin
    match_address = 4'b0;
    match_found = 0;

    for(i = 0; i < (1 << address_line); i = i+1) begin
        if(!match_found) begin
            match_count = 0;
            data = register_file[i];
            mask = dont_care_register_file[i];

            for (j = 0; j < data_size; j = j+1) begin
                if(!mask[j])
                    match_count = match_count+1;

                else if(data[j] == input_data[j])
                    match_count = match_count+1;
            end

            if(match_count == data_size) begin
                match_address = i;
                match_found = 1;
            end
        end
    end
end

endmodule

Ex9/codes/TCAM_TB.v

`define data_size 16
`define address_line 4

module TCAM_TB ();

parameter data_size = `data_size;
parameter address_line = `address_line;

reg [data_size-1:0] input_data;
reg clk = 0;
wire [address_line-1:0] match_address;
wire match_found;

TCAM tcam1(input_data, clk, match_address, match_found);

always 
    #5 clk = ~clk;

initial begin
    $dumpfile("TCAM_TB.vcd");
    $dumpvars;
end

initial begin
    input_data = 16'b1111111111111111;
    #10 $display("match address: %d, found: %b", match_address, match_found);

    input_data = 16'b1001001001001001;
    #10 $display("match address: %d, found: %b", match_address, match_found);

    input_data = 16'b0101101001011010;
    #10 $display("match address: %d, found: %b", match_address, match_found);

    input_data = 16'b1111110011001100;
    #10 $display("match address: %d, found: %b", match_address, match_found);

    input_data = 16'b0111000001110000;
    #10 $display("match address: %d, found: %b", match_address, match_found);

    input_data = 16'b1001011010010110;
    #10 $display("match address: %d, found: %b", match_address, match_found);

    input_data = 16'b1010101010101010;
    #10 $display("match address: %d, found: %b", match_address, match_found);

    input_data = 16'b1111001110011110;
    #10 $display("match address: %d, found: %b", match_address, match_found);
    $finish;
end

endmodule

Ex9/codes/TCAM_TB.vcd
$date
	Wed May 15 02:10:37 2024
$end
$version
	Icarus Verilog
$end
$timescale
	1s
$end
$scope module TCAM_TB $end
$var wire 1 ! match_found $end
$var wire 4 " match_address [3:0] $end
$var parameter 32 # address_line $end
$var parameter 32 $ data_size $end
$var reg 1 % clk $end
$var reg 16 & input_data [15:0] $end
$scope module tcam1 $end
$var wire 1 % clk $end
$var wire 16 ' input_data [15:0] $end
$var parameter 32 ( address_line $end
$var parameter 32 ) data_size $end
$var reg 16 * data [15:0] $end
$var reg 16 + mask [15:0] $end
$var reg 4 , match_address [3:0] $end
$var reg 1 ! match_found $end
$var integer 32 - i [31:0] $end
$var integer 32 . j [31:0] $end
$var integer 32 / match_count [31:0] $end
$upscope $end
$upscope $end
$enddefinitions $end
$comment Show the parameter values. $end
$dumpall
b10000 )
b100 (
b10000 $
b100 #
$end
#0
$dumpvars
bx /
bx .
bx -
bx ,
bx +
bx *
b1111111111111111 '
b1111111111111111 &
0%
bx "
x!
$end
#5
b10000 .
b1000111110001111 +
b1111111111111111 *
b10000 /
b10000 -
1!
b110 "
b110 ,
1%
#10
0%
b1001001001001001 &
b1001001001001001 '
#15
b10000 .
b1111111111111111 +
b1001001001001001 *
b10000 /
b10000 -
1!
b1 "
b1 ,
1%
#20
0%
b101101001011010 &
b101101001011010 '
#25
b1000111110001111 +
b10000 .
b11010011010011 *
b1010 /
b10000 -
0!
b0 "
b0 ,
1%
#30
0%
b1111110011001100 &
b1111110011001100 '
#35
1!
b10 "
b10 ,
b10000 .
b1100111111001111 +
b1100110011001100 *
b10000 /
b10000 -
1%
#40
0%
b111000001110000 &
b111000001110000 '
#45
b10000 .
b1000111110001111 +
b0 *
b10000 /
b10000 -
1!
b111 "
b111 ,
1%
#50
0%
b1001011010010110 &
b1001011010010110 '
#55
b10000 .
b11110000111100 +
b101010101010101 *
b10000 /
b10000 -
1!
b101 "
b101 ,
1%
#60
0%
b1010101010101010 &
b1010101010101010 '
#65
b10000 .
b1111111111111111 +
b1010101010101010 *
b10000 /
b10000 -
1!
b0 "
b0 ,
1%
#70
0%
b1111001110011110 &
b1111001110011110 '
#75
b11 "
b11 ,
b1100111111001111 +
b1110001110001110 *
b10000 .
b10000 /
b10000 -
1!
1%
